[
  {
    "id": "cmrp02ddq001199b2sq51x8ic",
    "country": "GB",
    "offerUrl": "https://www.af9m8trk.com/9D111B56/JCS12H4Z/?s1=",
    "isActive": true,
    "isGlobal": false,
    "userId": "cmrhjythj00003go8ads9k9xx",
    "createdAt": "2026-07-17T07:54:58.238Z",
    "updatedAt": "2026-07-17T07:54:58.238Z",
    "priority": 100,
    "rotationMode": "PRIORITY",
    "groupName": "MK1"
  },
  {
    "id": "cmrp02t0e001399b2xsn2nawp",
    "country": "GB",
    "offerUrl": "https://www.af9m8trk.com/9D111B56/JCS12H4Z/?s1=",
    "isActive": true,
    "isGlobal": false,
    "userId": "cmrhjythj00003go8ads9k9xx",
    "createdAt": "2026-07-17T07:55:18.494Z",
    "updatedAt": "2026-07-17T07:55:18.494Z",
    "priority": 100,
    "rotationMode": "PRIORITY",
    "groupName": "MK2"
  },
  {
    "id": "cmrp037om001599b22lkeil87",
    "country": "GB",
    "offerUrl": "https://www.af9m8trk.com/9D111B56/JCS12H4Z/?s1=",
    "isActive": true,
    "isGlobal": false,
    "userId": "cmrhjythj00003go8ads9k9xx",
    "createdAt": "2026-07-17T07:55:37.511Z",
    "updatedAt": "2026-07-17T07:55:37.511Z",
    "priority": 100,
    "rotationMode": "PRIORITY",
    "groupName": "MK3"
  },
  {
    "id": "cmrp03qj3001799b2vb6m4ktg",
    "country": "GB",
    "offerUrl": "https://www.af9m8trk.com/9D111B56/JCS12H4Z/?s1=",
    "isActive": true,
    "isGlobal": false,
    "userId": "cmrhjythj00003go8ads9k9xx",
    "createdAt": "2026-07-17T07:56:01.935Z",
    "updatedAt": "2026-07-17T07:56:01.935Z",
    "priority": 100,
    "rotationMode": "PRIORITY",
    "groupName": "MK4"
  },
  {
    "id": "cmrp043k2001999b2plhw7b3r",
    "country": "GB",
    "offerUrl": "https://www.af9m8trk.com/9D111B56/JCS12H4Z/?s1=",
    "isActive": true,
    "isGlobal": false,
    "userId": "cmrhjythj00003go8ads9k9xx",
    "createdAt": "2026-07-17T07:56:18.818Z",
    "updatedAt": "2026-07-17T07:56:18.818Z",
    "priority": 100,
    "rotationMode": "PRIORITY",
    "groupName": "MK5"
  },
  {
    "id": "cmrllhvdj00095quikjbbbqlg",
    "country": "GLOBAL",
    "offerUrl": "https://app.hawktrk.com/sl?id=6a2050db46d3cf0d62f32aa4&pid=2&sub2=u618429&sub6=s2smartLink&sub5=",
    "isActive": true,
    "isGlobal": true,
    "userId": "cmrhjythj00003go8ads9k9xx",
    "createdAt": "2026-07-14T22:43:48.632Z",
    "updatedAt": "2026-07-14T22:43:48.632Z",
    "priority": 100,
    "rotationMode": "PRIORITY",
    "groupName": "MK5"
  },
  {
    "id": "cmrhocb8z0001xgl2s6sxahg2",
    "country": "US",
    "offerUrl": "https://afefs.com/?s1=",
    "isActive": true,
    "isGlobal": false,
    "userId": "cmrg3i4tr00006au57r7ck9u2",
    "createdAt": "2026-07-12T04:52:23.411Z",
    "updatedAt": "2026-07-12T04:52:23.411Z",
    "priority": 100,
    "rotationMode": "PRIORITY",
    "groupName": "Ratul"
  },
  {
    "id": "cmrqeqbmj0001w8ggew9q3e9d",
    "country": "GLOBAL",
    "offerUrl": "https://app.hawktrk.com/sl?id=6a2050db46d3cf0d62f32aa4&pid=2&sub2=u811439&sub6=s2smartLink&sub5=",
    "isActive": true,
    "isGlobal": true,
    "userId": "cmrq4ahat0000l945atm4ovav",
    "createdAt": "2026-07-18T07:33:16.507Z",
    "updatedAt": "2026-07-18T07:33:16.507Z",
    "priority": 100,
    "rotationMode": "PRIORITY",
    "groupName": "OFFERWALL-1"
  },
  {
    "id": "cmrqeqs0y0003w8ggt64p9z0g",
    "country": "GLOBAL",
    "offerUrl": "https://app.hawktrk.com/sl?id=6a2050db46d3cf0d62f32aa4&pid=2&sub2=u811439&sub6=s2smartLink&sub5=",
    "isActive": true,
    "isGlobal": true,
    "userId": "cmrq4ahat0000l945atm4ovav",
    "createdAt": "2026-07-18T07:33:37.762Z",
    "updatedAt": "2026-07-18T07:33:37.762Z",
    "priority": 100,
    "rotationMode": "PRIORITY",
    "groupName": "OFFERWALL-2"
  },
  {
    "id": "cmrhocxjc0003xgl2puw6gpd4",
    "country": "GLOBAL",
    "offerUrl": "https://sdfsdfsd.com/?s1=",
    "isActive": true,
    "isGlobal": true,
    "userId": "cmrg3i4tr00006au57r7ck9u2",
    "createdAt": "2026-07-12T04:52:52.296Z",
    "updatedAt": "2026-07-12T04:53:36.664Z",
    "priority": 100,
    "rotationMode": "PRIORITY",
    "groupName": "Ratul"
  },
  {
    "id": "cmrhorwh60001673aat5n7g4e",
    "country": "AR",
    "offerUrl": "https://serrwei.com/?sa=",
    "isActive": true,
    "isGlobal": false,
    "userId": "cmrg3i4tr00006au57r7ck9u2",
    "createdAt": "2026-07-12T05:04:30.762Z",
    "updatedAt": "2026-07-12T05:04:30.762Z",
    "priority": 100,
    "rotationMode": "PRIORITY",
    "groupName": "Ratul"
  },
  {
    "id": "cmrqgrllc0001q97roqkonbec",
    "country": "US",
    "offerUrl": "https://www.af9m8trk.com/AXV114Z2/2G211TKZ/?s1=",
    "isActive": true,
    "isGlobal": false,
    "userId": "cmrq4ahat0000l945atm4ovav",
    "createdAt": "2026-07-18T08:30:15.311Z",
    "updatedAt": "2026-07-18T08:30:15.311Z",
    "priority": 100,
    "rotationMode": "PRIORITY",
    "groupName": "OFFERWALL-1"
  },
  {
    "id": "cmrqgtimr0003q97rvg5ave2t",
    "country": "US",
    "offerUrl": "https://www.af9m8trk.com/AXV114Z2/TTR12295/?s1=",
    "isActive": true,
    "isGlobal": false,
    "userId": "cmrq4ahat0000l945atm4ovav",
    "createdAt": "2026-07-18T08:31:44.788Z",
    "updatedAt": "2026-07-18T08:31:44.788Z",
    "priority": 100,
    "rotationMode": "PRIORITY",
    "groupName": "OFFERWALL-2"
  },
  {
    "id": "cmrqgy2s60005q97rf17yolvv",
    "country": "CA",
    "offerUrl": "https://www.af9m8trk.com/AXV114Z2/P4612FSW/?s1=",
    "isActive": true,
    "isGlobal": false,
    "userId": "cmrq4ahat0000l945atm4ovav",
    "createdAt": "2026-07-18T08:35:17.527Z",
    "updatedAt": "2026-07-18T08:35:17.527Z",
    "priority": 100,
    "rotationMode": "PRIORITY",
    "groupName": "OFFERWALL-1"
  },
  {
    "id": "cmrqgyj970007q97r3fm6brt3",
    "country": "CA",
    "offerUrl": "https://www.af9m8trk.com/AXV114Z2/P4612FSW/?s1=",
    "isActive": true,
    "isGlobal": false,
    "userId": "cmrq4ahat0000l945atm4ovav",
    "createdAt": "2026-07-18T08:35:38.875Z",
    "updatedAt": "2026-07-18T08:35:38.875Z",
    "priority": 100,
    "rotationMode": "PRIORITY",
    "groupName": "OFFERWALL-2"
  },
  {
    "id": "cmrqgz2500009q97rwqjhlgfc",
    "country": "AU",
    "offerUrl": "https://www.af9m8trk.com/AXV114Z2/4WY12H55/?s1=",
    "isActive": true,
    "isGlobal": false,
    "userId": "cmrq4ahat0000l945atm4ovav",
    "createdAt": "2026-07-18T08:36:03.349Z",
    "updatedAt": "2026-07-18T08:37:28.120Z",
    "priority": 100,
    "rotationMode": "PRIORITY",
    "groupName": "OFFERWALL-1"
  },
  {
    "id": "cmrqgza61000bq97rngnflog6",
    "country": "AU",
    "offerUrl": "https://www.af9m8trk.com/AXV114Z2/4WY12H55/?s1=",
    "isActive": true,
    "isGlobal": false,
    "userId": "cmrq4ahat0000l945atm4ovav",
    "createdAt": "2026-07-18T08:36:13.753Z",
    "updatedAt": "2026-07-18T08:37:38.987Z",
    "priority": 100,
    "rotationMode": "PRIORITY",
    "groupName": "OFFERWALL-2"
  },
  {
    "id": "cmrqh1yqh000dq97ryb5cqqnk",
    "country": "GB",
    "offerUrl": "https://www.af9m8trk.com/AXV114Z2/16F12BVJ/?s1=",
    "isActive": true,
    "isGlobal": false,
    "userId": "cmrq4ahat0000l945atm4ovav",
    "createdAt": "2026-07-18T08:38:18.905Z",
    "updatedAt": "2026-07-18T08:38:18.905Z",
    "priority": 100,
    "rotationMode": "PRIORITY",
    "groupName": "OFFERWALL-1"
  },
  {
    "id": "cmrqh267a000fq97rlkal0bw8",
    "country": "GB",
    "offerUrl": "https://www.af9m8trk.com/AXV114Z2/16F12BVJ/?s1=",
    "isActive": true,
    "isGlobal": false,
    "userId": "cmrq4ahat0000l945atm4ovav",
    "createdAt": "2026-07-18T08:38:28.582Z",
    "updatedAt": "2026-07-18T08:38:28.582Z",
    "priority": 100,
    "rotationMode": "PRIORITY",
    "groupName": "OFFERWALL-2"
  },
  {
    "id": "cmrozs1e0000799b2zv8oh2i8",
    "country": "US",
    "offerUrl": "https://www.af9m8trk.com/9D111B56/2G211TKZ/?s1=",
    "isActive": true,
    "isGlobal": false,
    "userId": "cmrhjythj00003go8ads9k9xx",
    "createdAt": "2026-07-17T07:46:56.136Z",
    "updatedAt": "2026-07-21T07:27:10.050Z",
    "priority": 100,
    "rotationMode": "PRIORITY",
    "groupName": "MK3"
  },
  {
    "id": "cmrozt0vp000999b2vkm58brl",
    "country": "US",
    "offerUrl": "https://www.af9m8trk.com/9D111B56/2G211TKZ/?s1=",
    "isActive": true,
    "isGlobal": false,
    "userId": "cmrhjythj00003go8ads9k9xx",
    "createdAt": "2026-07-17T07:47:42.134Z",
    "updatedAt": "2026-07-21T07:27:22.676Z",
    "priority": 100,
    "rotationMode": "PRIORITY",
    "groupName": "MK4"
  },
  {
    "id": "cmrozwhpi000l99b2h84f53ks",
    "country": "US",
    "offerUrl": "https://www.af9m8trk.com/9D111B56/2G211TKZ/?s1=",
    "isActive": true,
    "isGlobal": false,
    "userId": "cmrhjythj00003go8ads9k9xx",
    "createdAt": "2026-07-17T07:50:23.910Z",
    "updatedAt": "2026-07-21T07:27:35.832Z",
    "priority": 100,
    "rotationMode": "PRIORITY",
    "groupName": "MK5"
  },
  {
    "id": "cmrozr567000399b24kskjemo",
    "country": "US",
    "offerUrl": "https://www.af9m8trk.com/9D111B56/2G211TKZ/?s1=",
    "isActive": true,
    "isGlobal": false,
    "userId": "cmrhjythj00003go8ads9k9xx",
    "createdAt": "2026-07-17T07:46:14.384Z",
    "updatedAt": "2026-07-21T07:26:15.253Z",
    "priority": 100,
    "rotationMode": "PRIORITY",
    "groupName": "MK1"
  },
  {
    "id": "cmrllg6ni00015quiuu2fogd6",
    "country": "GLOBAL",
    "offerUrl": "https://app.hawktrk.com/sl?id=6a2050db46d3cf0d62f32aa4&pid=2&sub2=u618429&sub6=s2smartLink&sub5=",
    "isActive": true,
    "isGlobal": true,
    "userId": "cmrhjythj00003go8ads9k9xx",
    "createdAt": "2026-07-14T22:42:29.933Z",
    "updatedAt": "2026-07-14T22:42:29.933Z",
    "priority": 100,
    "rotationMode": "PRIORITY",
    "groupName": "MK1"
  },
  {
    "id": "cmrllgqm500035quislnp9ojr",
    "country": "GLOBAL",
    "offerUrl": "https://app.hawktrk.com/sl?id=6a2050db46d3cf0d62f32aa4&pid=2&sub2=u618429&sub6=s2smartLink&sub5=",
    "isActive": true,
    "isGlobal": true,
    "userId": "cmrhjythj00003go8ads9k9xx",
    "createdAt": "2026-07-14T22:42:55.806Z",
    "updatedAt": "2026-07-14T22:42:55.806Z",
    "priority": 100,
    "rotationMode": "PRIORITY",
    "groupName": "MK2"
  },
  {
    "id": "cmrllgzhz00055quivzabayzg",
    "country": "GLOBAL",
    "offerUrl": "https://app.hawktrk.com/sl?id=6a2050db46d3cf0d62f32aa4&pid=2&sub2=u618429&sub6=s2smartLink&sub5=",
    "isActive": true,
    "isGlobal": true,
    "userId": "cmrhjythj00003go8ads9k9xx",
    "createdAt": "2026-07-14T22:43:07.320Z",
    "updatedAt": "2026-07-14T22:43:07.320Z",
    "priority": 100,
    "rotationMode": "PRIORITY",
    "groupName": "MK3"
  },
  {
    "id": "cmrllhdpz00075quiw5w2y07v",
    "country": "GLOBAL",
    "offerUrl": "https://app.hawktrk.com/sl?id=6a2050db46d3cf0d62f32aa4&pid=2&sub2=u618429&sub6=s2smartLink&sub5=",
    "isActive": true,
    "isGlobal": true,
    "userId": "cmrhjythj00003go8ads9k9xx",
    "createdAt": "2026-07-14T22:43:25.751Z",
    "updatedAt": "2026-07-14T22:43:25.751Z",
    "priority": 100,
    "rotationMode": "PRIORITY",
    "groupName": "MK4"
  },
  {
    "id": "cmrozrkeq000599b2ib9n8x3u",
    "country": "US",
    "offerUrl": "https://www.af9m8trk.com/9D111B56/2G211TKZ/?s1=",
    "isActive": true,
    "isGlobal": false,
    "userId": "cmrhjythj00003go8ads9k9xx",
    "createdAt": "2026-07-17T07:46:34.130Z",
    "updatedAt": "2026-07-21T07:26:27.380Z",
    "priority": 100,
    "rotationMode": "PRIORITY",
    "groupName": "MK2"
  },
  {
    "id": "cmroztvij000b99b27govho6e",
    "country": "AU",
    "offerUrl": "https://www.af9m8trk.com/9D111B56/4WY12H55/?s1=",
    "isActive": true,
    "isGlobal": false,
    "userId": "cmrhjythj00003go8ads9k9xx",
    "createdAt": "2026-07-17T07:48:21.836Z",
    "updatedAt": "2026-07-17T07:48:21.836Z",
    "priority": 100,
    "rotationMode": "PRIORITY",
    "groupName": "MK1"
  },
  {
    "id": "cmrozuh7s000d99b24o9cpugk",
    "country": "AU",
    "offerUrl": "https://www.af9m8trk.com/9D111B56/4WY12H55/?s1=",
    "isActive": true,
    "isGlobal": false,
    "userId": "cmrhjythj00003go8ads9k9xx",
    "createdAt": "2026-07-17T07:48:49.961Z",
    "updatedAt": "2026-07-17T07:48:49.961Z",
    "priority": 100,
    "rotationMode": "PRIORITY",
    "groupName": "MK2"
  },
  {
    "id": "cmrozurlh000f99b2kkr07qv4",
    "country": "AU",
    "offerUrl": "https://www.af9m8trk.com/9D111B56/4WY12H55/?s1=",
    "isActive": true,
    "isGlobal": false,
    "userId": "cmrhjythj00003go8ads9k9xx",
    "createdAt": "2026-07-17T07:49:03.414Z",
    "updatedAt": "2026-07-17T07:49:03.414Z",
    "priority": 100,
    "rotationMode": "PRIORITY",
    "groupName": "MK3"
  },
  {
    "id": "cmrozuzar000h99b2e1ffomwf",
    "country": "AU",
    "offerUrl": "https://www.af9m8trk.com/9D111B56/4WY12H55/?s1=",
    "isActive": true,
    "isGlobal": false,
    "userId": "cmrhjythj00003go8ads9k9xx",
    "createdAt": "2026-07-17T07:49:13.395Z",
    "updatedAt": "2026-07-17T07:49:13.395Z",
    "priority": 100,
    "rotationMode": "PRIORITY",
    "groupName": "MK4"
  },
  {
    "id": "cmrozv98p000j99b2wo2tk4q3",
    "country": "AU",
    "offerUrl": "https://www.af9m8trk.com/9D111B56/4WY12H55/?s1=",
    "isActive": true,
    "isGlobal": false,
    "userId": "cmrhjythj00003go8ads9k9xx",
    "createdAt": "2026-07-17T07:49:26.281Z",
    "updatedAt": "2026-07-17T07:49:26.281Z",
    "priority": 100,
    "rotationMode": "PRIORITY",
    "groupName": "MK5"
  },
  {
    "id": "cmrozxoxq000n99b22cfycfcg",
    "country": "CA",
    "offerUrl": "https://www.af9m8trk.com/9D111B56/P4612FSW/?s1=",
    "isActive": true,
    "isGlobal": false,
    "userId": "cmrhjythj00003go8ads9k9xx",
    "createdAt": "2026-07-17T07:51:19.934Z",
    "updatedAt": "2026-07-17T07:51:19.934Z",
    "priority": 100,
    "rotationMode": "PRIORITY",
    "groupName": "MK1"
  },
  {
    "id": "cmrozy4ur000p99b28bqph3hn",
    "country": "CA",
    "offerUrl": "https://www.af9m8trk.com/9D111B56/P4612FSW/?s1=",
    "isActive": true,
    "isGlobal": false,
    "userId": "cmrhjythj00003go8ads9k9xx",
    "createdAt": "2026-07-17T07:51:40.563Z",
    "updatedAt": "2026-07-17T07:51:40.563Z",
    "priority": 100,
    "rotationMode": "PRIORITY",
    "groupName": "MK2"
  },
  {
    "id": "cmrozygaj000r99b2tc541dvi",
    "country": "CA",
    "offerUrl": "https://www.af9m8trk.com/9D111B56/P4612FSW/?s1=",
    "isActive": true,
    "isGlobal": false,
    "userId": "cmrhjythj00003go8ads9k9xx",
    "createdAt": "2026-07-17T07:51:55.387Z",
    "updatedAt": "2026-07-17T07:51:55.387Z",
    "priority": 100,
    "rotationMode": "PRIORITY",
    "groupName": "MK3"
  },
  {
    "id": "cmrozz0de000t99b22jq0imzl",
    "country": "CA",
    "offerUrl": "https://www.af9m8trk.com/9D111B56/P4612FSW/?s1=",
    "isActive": true,
    "isGlobal": false,
    "userId": "cmrhjythj00003go8ads9k9xx",
    "createdAt": "2026-07-17T07:52:21.410Z",
    "updatedAt": "2026-07-17T07:52:21.410Z",
    "priority": 100,
    "rotationMode": "PRIORITY",
    "groupName": "MK4"
  },
  {
    "id": "cmrp00tn3000z99b27yoykduv",
    "country": "CA",
    "offerUrl": "https://www.af9m8trk.com/9D111B56/P4612FSW/?s1=",
    "isActive": true,
    "isGlobal": false,
    "userId": "cmrhjythj00003go8ads9k9xx",
    "createdAt": "2026-07-17T07:53:45.999Z",
    "updatedAt": "2026-07-17T07:53:45.999Z",
    "priority": 100,
    "rotationMode": "PRIORITY",
    "groupName": "MK5"
  }
]